physion/__init__.py
physion/__main__.py
physion/acquisition/__init__.py
physion/acquisition/gui.py
physion/acquisition/run.py
physion/acquisition/settings.py
physion/acquisition/tools.py
physion/acquisition/configs/Adrianna-Bacci-2P.json
physion/acquisition/configs/Jo-Bacci-2P.json
physion/acquisition/configs/Taddy-A1-2P.json
physion/acquisition/configs/Troubleshooting.json
physion/acquisition/configs/Yann-A1-2P.json
physion/acquisition/configs/Yann-Bacci-2P.json
physion/acquisition/protocols/FFDG-contrast-curve+blank.json
physion/acquisition/protocols/Light-Levels-Symmetric-5b-5g-10blank-5g-5b.json
physion/acquisition/protocols/Millman-et-al-2020.json
physion/acquisition/protocols/NDNF-protocol.json
physion/acquisition/protocols/black-grey-white-20s-each-x5.json
physion/acquisition/protocols/drifting-gratings.json
physion/acquisition/protocols/ff-gratings-2orientations-8contrasts-15repeats.json
physion/acquisition/protocols/ff-gratings-8orientation-2contrasts-15repeats.json
physion/acquisition/protocols/injection-monitoring.json
physion/acquisition/protocols/old-NDNF-protocol.json
physion/acquisition/protocols/quick-spatial-mapping.json
physion/acquisition/protocols/size-tuning-protocol-linear.json
physion/acquisition/protocols/size-tuning-protocol-log-long.json
physion/acquisition/protocols/size-tuning-protocol-log.json
physion/acquisition/protocols/size-tuning-protocol-long.json
physion/acquisition/protocols/spatial-mapping.json
physion/acquisition/protocols/stim-demo.json
physion/acquisition/recordings/Scan1Plane_Screen342V.py
physion/acquisition/recordings/Scan1Plane_Screen356VOffPeriodScan.py
physion/acquisition/recordings/__init__.py
physion/analysis/__init__.py
physion/analysis/behavior.py
physion/analysis/dataframe.py
physion/analysis/process_NWB.py
physion/analysis/read_NWB.py
physion/analysis/stat_tools.py
physion/analysis/summary_pdf.py
physion/analysis/tools.py
physion/analysis/trial_averaging.py
physion/analysis/protocols/FFDG.py
physion-1.2.1.dist-info/LICENSE
physion-1.2.1.dist-info/METADATA
physion-1.2.1.dist-info/WHEEL
physion-1.2.1.dist-info/top_level.txt
physion-1.2.1.dist-info/RECORD
