Metadata-Version: 2.2
Name: physion
Version: 1.2.1
Summary: Vision Physiology Software
Author-email: Yann Zerlaut <yann.zerlaut@gmail.com>
Project-URL: Homepage, https://github.com/yzerlaut/physion
Project-URL: Documentation, https://github.com/yzerlaut/physion/README.md
Project-URL: Bug Tracker, https://github.com/yzerlaut/physion/issues
Classifier: Programming Language :: Python :: 3
Classifier: License :: OSI Approved :: MIT License
Classifier: Operating System :: OS Independent
Requires-Python: >=3.9.5
License-File: LICENSE
Requires-Dist: numpy
Requires-Dist: numba
Requires-Dist: scipy
Requires-Dist: matplotlib
Requires-Dist: scikit-image
Requires-Dist: natsort
Requires-Dist: pynwb
Requires-Dist: pandas>=1.4.4
Requires-Dist: pyqt5.sip
Requires-Dist: pyqtgraph
Requires-Dist: pyqtdarktheme
Requires-Dist: opencv-python
Requires-Dist: opencv-contrib-python
Requires-Dist: ffmpeg-python
Requires-Dist: pyqt5
Requires-Dist: openpyxl
